LICENSE
README.md
pyproject.toml
setup.py
src/pm_python.egg-info/PKG-INFO
src/pm_python.egg-info/SOURCES.txt
src/pm_python.egg-info/dependency_links.txt
src/pm_python.egg-info/top_level.txt
src/pyportmidi/__init__.py
src/pyportmidi/_pyportmidi.pyx
src/pyportmidi/midi.py